{
  "project_info": {
    "project_number": "152293997203",
    "firebase_url": "https://salahatlas-3c727-default-rtdb.firebaseio.com",
    "project_id": "salahatlas-3c727",
    "storage_bucket": "salahatlas-3c727.firebasestorage.app"
  },
  "client": [
    {
      "client_info": {
        "mobilesdk_app_id": "1:152293997203:android:674facadf09d687486ab66",
        "android_client_info": {
          "package_name": "dev.expo.frontend"
        }
      },
      "oauth_client": [],
      "api_key": [
        {
          "current_key": "AIzaSyDoeWuna2hJdkJK6dCqYAQnfPC7vmxF40s"
        }
      ],
      "services": {
        "appinvite_service": {
          "other_platform_oauth_client": []
        }
      }
    }
  ],
  "configuration_version": "1"
}